{
  "test_stock": "AJISF",
  "num_test_windows": 500,
  "timestamp": "20251120_013331",
  "total_combinations": 24,
  "completed_tests": 15,
  "results": [
    {
      "lookback": 50,
      "lookahead": 10,
      "stride": 1,
      "depth": 300,
      "total_time": 362.90505599975586,
      "avg_time_per_window": 0.7250918116569519,
      "total_return": 0.0,
      "sharpe_ratio": 0,
      "max_drawdown": 0.0,
      "avg_rl_reward": 0.9997384237280096,
      "final_portfolio_value": 1000000.0,
      "num_windows_completed": 500,
      "success": true,
      "error": null,
      "is_current_config": false,
      "test_order": 1
    },
    {
      "lookback": 50,
      "lookahead": 10,
      "stride": 1,
      "depth": 800,
      "total_time": 366.11980080604553,
      "avg_time_per_window": 0.7321883249282837,
      "total_return": 0.0,
      "sharpe_ratio": 0,
      "max_drawdown": 0.0,
      "avg_rl_reward": 0.9997384237280096,
      "final_portfolio_value": 1000000.0,
      "num_windows_completed": 500,
      "success": true,
      "error": null,
      "is_current_config": false,
      "test_order": 2
    },
    {
      "lookback": 50,
      "lookahead": 10,
      "stride": 2,
      "depth": 300,
      "total_time": 175.631117105484,
      "avg_time_per_window": 0.7024687061309814,
      "total_return": 0.0,
      "sharpe_ratio": 0,
      "max_drawdown": 0.0,
      "avg_rl_reward": 0.9958750754714447,
      "final_portfolio_value": 1000000.0,
      "num_windows_completed": 250,
      "success": true,
      "error": null,
      "is_current_config": false,
      "test_order": 3
    },
    {
      "lookback": 50,
      "lookahead": 10,
      "stride": 2,
      "depth": 800,
      "total_time": 174.93931818008423,
      "avg_time_per_window": 0.6996808567047119,
      "total_return": 0.0,
      "sharpe_ratio": 0,
      "max_drawdown": 0.0,
      "avg_rl_reward": 0.9958750754714447,
      "final_portfolio_value": 1000000.0,
      "num_windows_completed": 250,
      "success": true,
      "error": null,
      "is_current_config": false,
      "test_order": 4
    },
    {
      "lookback": 50,
      "lookahead": 10,
      "stride": 5,
      "depth": 300,
      "total_time": 66.14974904060364,
      "avg_time_per_window": 0.6613598489761352,
      "total_return": 0.0,
      "sharpe_ratio": 0,
      "max_drawdown": 0.0,
      "avg_rl_reward": 0.9993000011841537,
      "final_portfolio_value": 1000000.0,
      "num_windows_completed": 100,
      "success": true,
      "error": null,
      "is_current_config": false,
      "test_order": 5
    },
    {
      "lookback": 50,
      "lookahead": 10,
      "stride": 5,
      "depth": 800,
      "total_time": 66.07402110099792,
      "avg_time_per_window": 0.6605048155784607,
      "total_return": 0.0,
      "sharpe_ratio": 0,
      "max_drawdown": 0.0,
      "avg_rl_reward": 0.9993000011841537,
      "final_portfolio_value": 1000000.0,
      "num_windows_completed": 100,
      "success": true,
      "error": null,
      "is_current_config": false,
      "test_order": 6
    },
    {
      "lookback": 50,
      "lookahead": 20,
      "stride": 1,
      "depth": 300,
      "total_time": 372.7649691104889,
      "avg_time_per_window": 0.7454997458457947,
      "total_return": 0.0,
      "sharpe_ratio": 0,
      "max_drawdown": 0.0,
      "avg_rl_reward": 0.9987960793448142,
      "final_portfolio_value": 1000000.0,
      "num_windows_completed": 500,
      "success": true,
      "error": null,
      "is_current_config": false,
      "test_order": 7
    },
    {
      "lookback": 50,
      "lookahead": 20,
      "stride": 1,
      "depth": 800,
      "total_time": 373.53012561798096,
      "avg_time_per_window": 0.7470112524032593,
      "total_return": 0.0,
      "sharpe_ratio": 0,
      "max_drawdown": 0.0,
      "avg_rl_reward": 0.9987960793448142,
      "final_portfolio_value": 1000000.0,
      "num_windows_completed": 500,
      "success": true,
      "error": null,
      "is_current_config": false,
      "test_order": 8
    },
    {
      "lookback": 50,
      "lookahead": 20,
      "stride": 2,
      "depth": 300,
      "total_time": 181.43772506713867,
      "avg_time_per_window": 0.7256548414230347,
      "total_return": 0.0,
      "sharpe_ratio": 0,
      "max_drawdown": 0.0,
      "avg_rl_reward": 0.9992845528081814,
      "final_portfolio_value": 1000000.0,
      "num_windows_completed": 250,
      "success": true,
      "error": null,
      "is_current_config": false,
      "test_order": 9
    },
    {
      "lookback": 50,
      "lookahead": 20,
      "stride": 2,
      "depth": 800,
      "total_time": 182.35511922836304,
      "avg_time_per_window": 0.7293269910812378,
      "total_return": 0.0,
      "sharpe_ratio": 0,
      "max_drawdown": 0.0,
      "avg_rl_reward": 0.9992845528081814,
      "final_portfolio_value": 1000000.0,
      "num_windows_completed": 250,
      "success": true,
      "error": null,
      "is_current_config": false,
      "test_order": 10
    },
    {
      "lookback": 50,
      "lookahead": 20,
      "stride": 5,
      "depth": 300,
      "total_time": 70.84578514099121,
      "avg_time_per_window": 0.7082144594192505,
      "total_return": -0.20422525,
      "sharpe_ratio": -1.5954480704349319,
      "max_drawdown": 0.20422525,
      "avg_rl_reward": 0.995219720381676,
      "final_portfolio_value": 795774.75,
      "num_windows_completed": 100,
      "success": true,
      "error": null,
      "is_current_config": false,
      "test_order": 11
    },
    {
      "lookback": 50,
      "lookahead": 20,
      "stride": 5,
      "depth": 800,
      "total_time": 70.77590680122375,
      "avg_time_per_window": 0.7075133681297302,
      "total_return": -0.20422525,
      "sharpe_ratio": -1.5954480704349319,
      "max_drawdown": 0.20422525,
      "avg_rl_reward": 0.995219720381676,
      "final_portfolio_value": 795774.75,
      "num_windows_completed": 100,
      "success": true,
      "error": null,
      "is_current_config": false,
      "test_order": 12
    },
    {
      "lookback": 100,
      "lookahead": 10,
      "stride": 1,
      "depth": 300,
      "total_time": 540.6438829898834,
      "avg_time_per_window": 1.0812360033988953,
      "total_return": 0.0,
      "sharpe_ratio": 0,
      "max_drawdown": 0.0,
      "avg_rl_reward": 0.9996259048959272,
      "final_portfolio_value": 1000000.0,
      "num_windows_completed": 500,
      "success": true,
      "error": null,
      "is_current_config": false,
      "test_order": 13
    },
    {
      "lookback": 100,
      "lookahead": 10,
      "stride": 1,
      "depth": 800,
      "total_time": 540.8826088905334,
      "avg_time_per_window": 1.0817152915000916,
      "total_return": 0.0,
      "sharpe_ratio": 0,
      "max_drawdown": 0.0,
      "avg_rl_reward": 0.9996259048959272,
      "final_portfolio_value": 1000000.0,
      "num_windows_completed": 500,
      "success": true,
      "error": null,
      "is_current_config": false,
      "test_order": 14
    },
    {
      "lookback": 100,
      "lookahead": 10,
      "stride": 2,
      "depth": 300,
      "total_time": 236.49251508712769,
      "avg_time_per_window": 0.9458691787719726,
      "total_return": 0.0,
      "sharpe_ratio": 0,
      "max_drawdown": 0.0,
      "avg_rl_reward": 0.9996391231960764,
      "final_portfolio_value": 1000000.0,
      "num_windows_completed": 250,
      "success": true,
      "error": null,
      "is_current_config": false,
      "test_order": 15
    }
  ]
}